{"insuranceusers":[{"id":1,"name":"Ivan","surname":"Ivanov","patronymic":"Ivanovich "},{"id":2,"name":"Fedor","surname":"Fedorov","patronymic":"Fedorovich "},{"id":3,"name":"Ivan","surname":"Rakhimov","patronymic":"Ivanovich"},{"id":4,"name":"Василий","surname":"Васильев","patronymic":"Васильевич"},{"id":5,"name":"Ыцук","surname":"Васильев","patronymic":"Ваывыва"},{"id":6,"name":"цукцукыва","surname":"Ывацук","patronymic":"йуываы"},{"id":7,"name":"asdfasdf","surname":"sdfsdf","patronymic":"sdfsdf"},{"id":8,"name":"Iveqwrwan","surname":"sdfsdov","patronymic":"Ivsdfvxanovich"},{"id":9,"name":"qweeqwe","surname":"Ivanov","patronymic":"dcvxcv"},{"id":10,"name":"Ivaqweqwen","surname":"Ivanovwesdfvxcv","patronymic":"Ivanxcvwerovich"},{"id":11,"name":"Ivsadfweran","surname":"Ivasdfanov","patronymic":"Ivaasdfasdfnovich"},{"id":12,"name":"Ivansdfaasdf","surname":"Ivanwerweov","patronymic":"Ivanweqrwqerovich"},{"id":13,"name":"Ivqwwwwan","surname":"Ivaasdfnov","patronymic":"Ivwwwanovich"},{"id":14,"name":"Ivqqwerwwwwan  ","surname":"Ivaasasdfasdfdfnov","patronymic":"Ivqwerwwwanovichsdf"},{"id":15,"name":"asdf","surname":"asdf","patronymic":"rwqe"},{"id":16},{"id":17,"name":"","surname":"","patronymic":""},{"id":18,"surname":"asd","patronymic":""},{"id":19,"surname":"","patronymic":"213"},{"id":20,"name":"Ivan","surname":"Ivan","patronymic":"Ivanovich"}]}